activated_notebook_importer/__init__.py
activated_notebook_importer/importer.py
activated_notebook_importer-1.0.0.dist-info/LICENSE
activated_notebook_importer-1.0.0.dist-info/METADATA
activated_notebook_importer-1.0.0.dist-info/WHEEL
activated_notebook_importer-1.0.0.dist-info/top_level.txt
activated_notebook_importer-1.0.0.dist-info/RECORD
