Metadata-Version: 2.1
Name: activated-notebook-importer
Version: 1.0.0
Summary: An Activated AI utility for importing Jupyter notebooks as Python modules
Author-email: Activated AI <contact@activated-ai.com>
License: MIT License
Project-URL: Homepage, https://activated-ai.com
Keywords: activated ai,jupyter,notebook,import,module
Classifier: License :: OSI Approved :: MIT License
Classifier: Programming Language :: Python
Classifier: Programming Language :: Python :: 3
Requires-Python: >=3.8
License-File: LICENSE
Requires-Dist: nbformat
Requires-Dist: nbparameterise
Provides-Extra: dev
Requires-Dist: pytest; extra == "dev"
